amlhpc/__init__.py
amlhpc/__main__.py
amlhpc/pbs/qsub.py
amlhpc/slurm/sbatch.py
amlhpc/slurm/sinfo.py
amlhpc/slurm/squeue.py
amlhpc-0.2.2.dist-info/METADATA
amlhpc-0.2.2.dist-info/WHEEL
amlhpc-0.2.2.dist-info/entry_points.txt
amlhpc-0.2.2.dist-info/RECORD
