Metadata-Version: 2.1
Name: amlhpc
Version: 0.2.2
Summary: Emulate Slurm/PBS/LSF HPC scheduler in Azure ML
Author: Hugo Meiland
Author-email: hugo.meiland@microsoft.com
Requires-Python: >=3.8,<4.0
Classifier: Programming Language :: Python :: 3
Classifier: Programming Language :: Python :: 3.8
Classifier: Programming Language :: Python :: 3.9
Classifier: Programming Language :: Python :: 3.10
Classifier: Programming Language :: Python :: 3.11
Classifier: Programming Language :: Python :: 3.12
Requires-Dist: azure-ai-ml (>=1.12.1,<2.0.0)
